README.md
setup.cfg
setup.py
lemon/__init__.py
lemon/app.py
lemon/asgi.py
lemon/config.py
lemon/const.py
lemon/context.py
lemon/exception.py
lemon/log.py
lemon/middleware.py
lemon/parsers.py
lemon/request.py
lemon/response.py
lemon/router.py
lemon/server.py
pylemon.egg-info/PKG-INFO
pylemon.egg-info/SOURCES.txt
pylemon.egg-info/dependency_links.txt
pylemon.egg-info/requires.txt
pylemon.egg-info/top_level.txt