Metadata-Version: 1.1
Name: pylemon
Version: 0.2.2
Summary: An async and lightweight API framework for python .
Home-page: https://github.com/joway/lemon
Author: Joway Wang
Author-email: joway.w@gmail.com
License: MIT
Keywords: lemon restful api async python
Platform: UNKNOWN
Classifier: Development Status :: 4 - Beta
Classifier: Framework :: AsyncIO
Classifier: License :: OSI Approved :: MIT License
Classifier: Natural Language :: English
Classifier: Topic :: Software Development :: Libraries :: Application Frameworks
Classifier: Intended Audience :: Developers
Classifier: Intended Audience :: Information Technology
Classifier: Operating System :: OS Independent
Classifier: Programming Language :: Python
Classifier: Programming Language :: Python :: 3.6
